{
    "id": "94da910f333c35c823b78286c6eecb7d",
    "name": "Esme",
    "description": null,
    "auth": null,
    "events": null,
    "variables": [],
    "order": [],
    "folders_order": [],
    "folders": [],
    "requests": [
        {
            "id": "cf1984a04ab0bf69b5ca379ecaff3fbd",
            "name": "Get Unsecured SME Loans",
            "url": "httpsopenapi.esmeloans.comopen-banking\/v2.1\/unsecured-sme-loans\/",
            "description": "This endpoint can contain multiple brands owned by a particular banking group. Each brand can own multiple SME Unsecured Loan products.",
            "data": [],
            "dataMode": "raw",
            "headerData": null,
            "method": "get",
            "pathVariableData": [],
            "queryParams": [],
            "auth": null,
            "events": null,
            "folder": null,
            "protocolProfileBehavior": {
                "disableBodyPruning": true
            },
            "responses": [],
            "currentHelper": null,
            "helperAttributes": null,
            "collectionId": "94da910f333c35c823b78286c6eecb7d",
            "rawModeData": ""
        }
    ]
}